cocoscore/__init__.py
cocoscore/ml/__init__.py
cocoscore/ml/cv.py
cocoscore/ml/distance_scores.py
cocoscore/ml/evaluation.py
cocoscore/ml/fasttext_helpers.py
cocoscore/ml/metrics.py
cocoscore/ml/tools.py
cocoscore/ml/feature/__init__.py
cocoscore/ml/feature/embedding_matrix.py
cocoscore/ml/feature/glove.py
cocoscore/tagger/__init__.py
cocoscore/tagger/co_occurrence_score.py
cocoscore/tagger/entity_mappers.py
cocoscore/tools/__init__.py
cocoscore/tools/constants.py
cocoscore/tools/data_tools.py
cocoscore/tools/file_tools.py
cocoscore-1.0.0.dist-info/AUTHORS.rst
cocoscore-1.0.0.dist-info/LICENSE
cocoscore-1.0.0.dist-info/METADATA
cocoscore-1.0.0.dist-info/WHEEL
cocoscore-1.0.0.dist-info/top_level.txt
cocoscore-1.0.0.dist-info/RECORD
