Metadata-Version: 2.1
Name: cocoscore
Version: 1.0.0
Summary: CoCoScore: context-aware co-occurrence scores for text mining applications
Home-page: https://github.com/JungeAlexander/cocoscore
Author: Alexander Junge
Author-email: alexander.junge@posteo.net
License: MIT license
Platform: UNKNOWN
Classifier: Development Status :: 5 - Production/Stable
Classifier: Intended Audience :: Developers
Classifier: License :: OSI Approved :: MIT License
Classifier: Operating System :: Unix
Classifier: Operating System :: POSIX
Classifier: Operating System :: Microsoft :: Windows
Classifier: Programming Language :: Python
Classifier: Programming Language :: Python :: 3.5
Classifier: Programming Language :: Python :: 3.6
Classifier: Programming Language :: Python :: 3.7
Classifier: Programming Language :: Python :: Implementation :: CPython
Classifier: Topic :: Utilities
Requires-Dist: pandas (>=0.23.3)
Requires-Dist: scikit-learn (>=0.20.1)
